rgptrxy/rgpt.py
rgptrxy-0.0.2.dist-info/LICENSE.txt
rgptrxy-0.0.2.dist-info/METADATA
rgptrxy-0.0.2.dist-info/WHEEL
rgptrxy-0.0.2.dist-info/top_level.txt
rgptrxy-0.0.2.dist-info/RECORD
