Metadata-Version: 2.1
Name: rgptrxy
Version: 0.0.2
Summary: gpt3.5
Author-email: rxy <1302553960@qq.com>
Classifier: Programming Language :: Python :: 3
Classifier: License :: OSI Approved :: MIT License
Classifier: Operating System :: OS Independent
Requires-Python: >=3.7
License-File: LICENSE.txt
